path_traveler/__init__.py
path_traveler/path_identifier.py
path_traveler/path_identifier_cli.py
path_traveler-0.0.7.dist-info/LICENSE
path_traveler-0.0.7.dist-info/METADATA
path_traveler-0.0.7.dist-info/WHEEL
path_traveler-0.0.7.dist-info/entry_points.txt
path_traveler-0.0.7.dist-info/top_level.txt
path_traveler-0.0.7.dist-info/RECORD
