Metadata-Version: 2.1
Name: path-traveler
Version: 0.0.7
Summary: Travel any path and find some files.
Home-page: https://github.com/vhiwase/path-traveler
Author: Vaibhav Hiwase
Author-email: hiwase.vaibhav@gmail.com
License: MIT license
Keywords: path_traveler
Classifier: Development Status :: 4 - Beta
Classifier: Intended Audience :: Developers
Classifier: License :: OSI Approved :: MIT License
Classifier: Natural Language :: English
Classifier: Programming Language :: Python :: 3
Classifier: Programming Language :: Python :: 3.6
Classifier: Programming Language :: Python :: 3.7
Classifier: Programming Language :: Python :: 3.8
Classifier: Programming Language :: Python :: 3.9
Classifier: Programming Language :: Python :: 3.10
Classifier: Programming Language :: Python :: 3.11
Requires-Python: >=3.6
License-File: LICENSE
Requires-Dist: click >=7.1.2
Requires-Dist: pathlib >=1.0.1
